etc/init.d/vc3-infoservice.init
etc/logrotate.d/vc3-infoservice
etc/sysconfig/vc3-infoservice
etc/vc3/vc3-infoclient.conf
etc/vc3/vc3-infoservice.conf
usr/lib/systemd/system/vc3-infoservice.service
vc3_info_service-2017.8.2.data/scripts/vc3-info-client
vc3_info_service-2017.8.2.data/scripts/vc3-info-service
vc3_info_service-2017.8.2.dist-info/DESCRIPTION.rst
vc3_info_service-2017.8.2.dist-info/METADATA
vc3_info_service-2017.8.2.dist-info/RECORD
vc3_info_service-2017.8.2.dist-info/WHEEL
vc3_info_service-2017.8.2.dist-info/metadata.json
vc3_info_service-2017.8.2.dist-info/top_level.txt
vc3infoservice/__init__.py
vc3infoservice/__init__.pyo
vc3infoservice/core.py
vc3infoservice/core.pyo
vc3infoservice/infoclient.py
vc3infoservice/infoclient.pyo
vc3infoservice/infoservice.py
vc3infoservice/infoservice.pyo
vc3infoservice/infoutil.py
vc3infoservice/infoutil.pyo
vc3infoservice/plugins/__init__.py
vc3infoservice/plugins/__init__.pyo
vc3infoservice/plugins/persist/CouchDB.py
vc3infoservice/plugins/persist/CouchDB.pyo
vc3infoservice/plugins/persist/DiskDump.py
vc3infoservice/plugins/persist/DiskDump.pyo
vc3infoservice/plugins/persist/Memory.py
vc3infoservice/plugins/persist/Memory.pyo
vc3infoservice/plugins/persist/SQLite.py
vc3infoservice/plugins/persist/SQLite.pyo
vc3infoservice/plugins/persist/__init__.py
vc3infoservice/plugins/persist/__init__.pyo
